odoo/addons/pos_order_remove_line/README.rst
odoo/addons/pos_order_remove_line/__init__.py
odoo/addons/pos_order_remove_line/__manifest__.py
odoo/addons/pos_order_remove_line/i18n/it.po
odoo/addons/pos_order_remove_line/i18n/pos_order_remove_line.pot
odoo/addons/pos_order_remove_line/readme/CONTRIBUTORS.rst
odoo/addons/pos_order_remove_line/readme/DESCRIPTION.rst
odoo/addons/pos_order_remove_line/static/description/icon.png
odoo/addons/pos_order_remove_line/static/description/index.html
odoo/addons/pos_order_remove_line/static/src/css/orderline.scss
odoo/addons/pos_order_remove_line/static/src/js/orderline.esm.js
odoo/addons/pos_order_remove_line/static/src/xml/orderline.xml
odoo_addon_pos_order_remove_line-16.0.1.2.2.dist-info/METADATA
odoo_addon_pos_order_remove_line-16.0.1.2.2.dist-info/WHEEL
odoo_addon_pos_order_remove_line-16.0.1.2.2.dist-info/top_level.txt
odoo_addon_pos_order_remove_line-16.0.1.2.2.dist-info/RECORD
